cdk_gw_tools/__init__.py
cdk_gw_tools/aws/__init__.py
cdk_gw_tools/aws/gw_handling.py
cdk_gw_tools/aws/secrets_rotation.py
cdk_gw_tools/cli/__init__.py
cdk_gw_tools/cli/auth.py
cdk_gw_tools/cli/interceptors.py
cdk_gw_tools/cli/main_parser.py
cdk_gw_tools/cli/plugins.py
cdk_gw_tools/cli/user_mappings.py
cdk_gw_tools/cli/vclusters_parser/__init__.py
cdk_gw_tools/cli/vclusters_parser/concentration_rules.py
cdk_gw_tools/cli_actions/__init__.py
cdk_gw_tools/cli_actions/auth.py
cdk_gw_tools/cli_actions/common.py
cdk_gw_tools/cli_actions/interceptors.py
cdk_gw_tools/cli_actions/plugins.py
cdk_gw_tools/cli_actions/user_mappings.py
cdk_gw_tools/cli_actions/vclusters/__init__.py
cdk_gw_tools/cli_actions/vclusters/topic_mappings.py
cdk_gw_tools/cli_tools/__init__.py
cdk_gw_tools/cli_tools/import_from_config.py
cdk_gw_tools/cli_tools/import_tenants_mappings.py
cdk_gw_tools/cli_tools/set_update_interceptors.py
cdk_gw_tools/cli_tools/user_mappings_tools.py
cdk_gw_tools/common/__init__.py
cdk_gw_tools/common/logging.py
cdk_gw_tools/specs/__init__.py
cdk_gw_tools/specs/interceptors-config.spec.json
cdk_gw_tools/specs/interceptors_config.py
cdk_gw_tools/specs/profiles_config.spec.json
cdk_gw_tools/specs/tenant_mappings-input.json
cdk_gw_tools/specs/user-mappings.spec.json
cdk_gw_tools/specs/user_mappings.py
cdk_gw_tools-3.0.0.dist-info/LICENSE
cdk_gw_tools-3.0.0.dist-info/METADATA
cdk_gw_tools-3.0.0.dist-info/WHEEL
cdk_gw_tools-3.0.0.dist-info/entry_points.txt
cdk_gw_tools-3.0.0.dist-info/RECORD
