Metadata-Version: 2.1
Name: cdk-gw-tools
Version: 3.0.0
Summary: Conduktor Proxy API Client
License: LICENSE
Keywords: compose-x,conduktor,kafka,proxy
Author: John "Preston" Mille
Author-email: john@ews-network.net
Requires-Python: >=3.9,<4.0
Classifier: Development Status :: 2 - Pre-Alpha
Classifier: Intended Audience :: Developers
Classifier: Intended Audience :: System Administrators
Classifier: License :: OSI Approved :: Apache Software License
Classifier: License :: Other/Proprietary License
Classifier: Natural Language :: English
Classifier: Programming Language :: Python :: 3
Classifier: Programming Language :: Python :: 3.9
Classifier: Programming Language :: Python :: 3.10
Classifier: Programming Language :: Python :: 3.11
Classifier: Programming Language :: Python :: 3.12
Requires-Dist: cdk-proxy-api-client (==3.0.0)
Requires-Dist: compose-x-common (>=1.4.7,<2.0.0)
Requires-Dist: dacite (>=1.8.1,<2.0.0)
Requires-Dist: importlib-resources (>=6.4,<7.0)
Requires-Dist: jsonschema (>=4.18)
Requires-Dist: pyyaml (>=6.0,<7.0)
Project-URL: Bug Tracker, https://github.com/JohnPreston/cdk-gw-tools/issues
Project-URL: Source (GitHub), https://github.com/JohnPreston/cdk-gw-tools
Project-URL: Source (CodeBerg), https://codeberg.org/JohnPreston/cdk-gw-tools
